maads-tml/__init__.py
maads-tml/sendfiles.py
maadstml/__init__.py
maadstml/readpdf.py
maadstml/sendfiles.py
maadstml/tmltextsummary.py
maadstml-3.66.dist-info/licenses/license.txt
maadstml-3.66.dist-info/METADATA
maadstml-3.66.dist-info/WHEEL
maadstml-3.66.dist-info/top_level.txt
maadstml-3.66.dist-info/RECORD
