Metadata-Version: 2.4
Name: maadstml
Version: 3.66
Summary: Multi-Agent Accelerator for Data Science (MAADS): Transactional Machine Learning
Home-page: https://github.com/smaurice101/transactionalmachinelearning
Author: Sebastian Maurice
Author-email: sebastian.maurice@otics.ca
License: MIT License
Keywords: genai, multi-agent, transactional machine learning, artificial intelligence, chatGPT, generative AI, privateGPT, data streams, data science, optimization, prescriptive analytics, machine learning, automl,auto-ml,artificial intelligence,predictive analytics,advanced analytics
License-File: license.txt
Requires-Dist: aiohttp>=3.6.2
Requires-Dist: requests>=2.22.0
Requires-Dist: validators>=0.14.2
Requires-Dist: wheel>=0.33.6
Requires-Dist: numpy>=1.18.1
Requires-Dist: pandas>=0.25.3
Requires-Dist: numpy-indexed>=0.3.5
Requires-Dist: nest_asyncio
Requires-Dist: pdfminer
Requires-Dist: binaryornot==0.4.4
Requires-Dist: selenium
Requires-Dist: async-timeout==5.0.1
Dynamic: author
Dynamic: author-email
Dynamic: description
Dynamic: description-content-type
Dynamic: home-page
Dynamic: keywords
Dynamic: license
Dynamic: license-file
Dynamic: requires-dist
Dynamic: summary
